fundb/__init__.py
fundb/fundb.py
fundb/test.py
fundb/test2.py
fundb-0.0.6.dist-info/LICENSE
fundb-0.0.6.dist-info/METADATA
fundb-0.0.6.dist-info/WHEEL
fundb-0.0.6.dist-info/top_level.txt
fundb-0.0.6.dist-info/RECORD
