Metadata-Version: 2.1
Name: fundb
Version: 0.0.6
Summary: Simple database for Python user
Home-page: https://github.com/Madhava-mng/FunDB
Author: Madhava-mng
Author-email: alformint@gmail.com
License: UNKNOWN
Platform: UNKNOWN
Classifier: License :: OSI Approved :: MIT License
Classifier: Operating System :: OS Independent
Requires-Dist: chipper-chicken
